Changes
LICENSE
MANIFEST.in
README.md
example.py
setup.cfg
setup.py
brain/admin.rs
brain/begin.rs
brain/clients.rs
brain/eliza.rs
brain/myself.rs
brain/python.rs
brain/rpg.rs
docs/api-objects.txt
docs/class-tree.html
docs/crarr.png
docs/epydoc.css
docs/epydoc.js
docs/frames.html
docs/help.html
docs/identifier-index.html
docs/index.html
docs/module-tree.html
docs/redirect.html
docs/rivescript-module.html
docs/rivescript-pysrc.html
docs/rivescript.RiveScript-class.html
docs/rivescript.__main__-module.html
docs/rivescript.__main__-pysrc.html
docs/rivescript.interactive-module.html
docs/rivescript.interactive-pysrc.html
docs/rivescript.python-module.html
docs/rivescript.python-pysrc.html
docs/rivescript.python.PyRiveObjects-class.html
docs/toc-everything.html
docs/toc-rivescript-module.html
docs/toc-rivescript.__main__-module.html
docs/toc-rivescript.interactive-module.html
docs/toc-rivescript.python-module.html
docs/toc.html
eg/javascript.py
eg/javascript.rs
python_rivescript.egg-info/PKG-INFO
python_rivescript.egg-info/SOURCES.txt
python_rivescript.egg-info/dependency_links.txt
python_rivescript.egg-info/requires.txt
python_rivescript.egg-info/top_level.txt
rivescript/__init__.py
rivescript/__main__.py
rivescript/interactive.py
rivescript/python.py