Metadata-Version: 1.1
Name: python-rivescript
Version: 1.04
Summary: A Chatterbot Scripting Language
Home-page: https://github.com/kirsle/rivescript-python
Author: Noah Petherbridge
Author-email: root@kirsle.net
License: Dual licensed; GPLv2
Keywords: bot chatbot chatterbot ai aiml chatscript buddyscript
Platform: UNKNOWN
Classifier: License :: OSI Approved :: GNU General Public License (GPL)
Classifier: Programming Language :: Python
Classifier: Development Status :: 5 - Production/Stable
Classifier: Intended Audience :: Developers
Classifier: Topic :: Scientific/Engineering :: Artificial Intelligence
